Workbook

Sheet Balance sheet
B2: INPUT | F2: BALANCE SHEET
B4: Parameters | C4: Value | F4: Years | G4: Opening Balance | H4: Gross Revenue | I4: Maintainance costs | J4: Leasing costs | K4: Net Revenue | L4: Balance PV | M4: Closing balance | N4: Installation/Decommision costs
B5: Investment Term (T) | C5: 35 | F5: 0 | G5: =-N5 -> -2.6857956e+08 | H5: 0 | I5: 0 | J5: 0 | K5: =H5-(I5+J5) -> 0 | L5: =M5*(IF(G5<0,(1/(1+$C$13/100)^(F5)),(1/(1+$C$13/100)^($C$27))*(1/(1+$C$14/100)^(F5-$C$27)))) -> -2.6857956e+08 | M5: =G5 -> -2.6857956e+08 | N5: =(IF($C$16="Offshore",$C$10*EXP(0.02*$C$6)*1.3,$C$10*EXP(0.02*$C$6)))*1000000*(1-$C$15/100) -> 2.6857956e+08
B6: Turbine Diameter (d) | C6: 245 | F6: 1 | G6: =M5 -> -2.6857956e+08 | H6: 0 | I6: =IF($C$6<30,'Maintainance data'!C5*$C$6,IF($C$6<100,'Maintainance data'!D5*$C$6,IF($C$6<=250,'Maintainance data'!E5," ")))*H6 -> 0 | J6: =IF($C$16="Offshore",(($C$8*0.1*$C$23)+(($C$9/100)*H6)),($C$8*$C$23)+(($C$9/100)*H6)) -> 266984.77 | K6: =H6-(I6+J6) -> -266984.77 | L6: =M6*(IF(G6<0,(1/(1+$C$13/100)^(F6)),(1/(1+$C$13/100)^($C$27))*(1/(1+$C$14/100)^(F6-$C$27)))) -> -2.6882792e+08 | M6: =IF(M5<0,M5*(1+$C$13/100),M5*(1+$C$14/100))+K6 -> -2.8899001e+08
B7: Average wind speed (w) | C7: 35 | F7: 2 | G7: =M6 -> -2.8899001e+08 | H7: =$C$11*(1+$C$12/100)^(F7-1)*$C$25*365*24 -> 88247504 | I7: =IF($C$6<30,'Maintainance data'!C5,IF($C$6<100,'Maintainance data'!D5,IF($C$6<=250,'Maintainance data'!E5," ")))*H7 -> 944248.29 | J7: =IF($C$16="Offshore",(($C$8*0.1*$C$23)+(($C$9/100)*H7)),($C$8*$C$23)+(($C$9/100)*H7)) -> 9091735.1 | K7: =H7-(I7+J7) -> 78211520 | L7: =M7*(IF(G7<0,(1/(1+$C$13/100)^(F7)),(1/(1+$C$13/100)^($C$27))*(1/(1+$C$14/100)^(F7-$C$27)))) -> -2.0114894e+08 | M7: =IF(M6<0,M6*(1+$C$13/100),M6*(1+$C$14/100))+K7 -> -2.3245274e+08
B8: Lease Price (PL) | C8: 12000 | F8: 3 | G8: =M7 -> -2.3245274e+08 | H8: =$C$11*(1+$C$12/100)^(F8-1)*$C$25*365*24 -> 91336166 | I8: =IF($C$6<30,'Maintainance data'!C6,IF($C$6<100,'Maintainance data'!D6,IF($C$6<=250,'Maintainance data'!E6," ")))*H8 -> 1808456.1 | J8: =IF($C$16="Offshore",(($C$8*0.1*$C$23)+(($C$9/100)*H8)),($C$8*$C$23)+(($C$9/100)*H8)) -> 9400601.4 | K8: =H8-(I8+J8) -> 80127109 | L8: =M8*(IF(G8<0,(1/(1+$C$13/100)^(F8)),(1/(1+$C$13/100)^($C$27))*(1/(1+$C$14/100)^(F8-$C$27)))) -> -1.3664978e+08 | M8: =IF(M7<0,M7*(1+$C$13/100),M7*(1+$C$14/100))+K8 -> -1.6975959e+08
B9: Lease commision rate (RL%) | C9: 10 | F9: 4 | G9: =M8 -> -1.6975959e+08 | H9: =$C$11*(1+$C$12/100)^(F9-1)*$C$25*365*24 -> 94532932 | I9: =IF($C$6<30,'Maintainance data'!C7,IF($C$6<100,'Maintainance data'!D7,IF($C$6<=250,'Maintainance data'!E7," ")))*H9 -> 2306603.5 | J9: =IF($C$16="Offshore",(($C$8*0.1*$C$23)+(($C$9/100)*H9)),($C$8*$C$23)+(($C$9/100)*H9)) -> 9720278 | K9: =H9-(I9+J9) -> 82506051 | L9: =M9*(IF(G9<0,(1/(1+$C$13/100)^(F9)),(1/(1+$C$13/100)^($C$27))*(1/(1+$C$14/100)^(F9-$C$27)))) -> -74869201 | M9: =IF(M8<0,M8*(1+$C$13/100),M8*(1+$C$14/100))+K9 -> -99985507
B10: Location cost factor (k) | C10: 2.5 | F10: 5 | G10: =M9 -> -99985507 | H10: =$C$11*(1+$C$12/100)^(F10-1)*$C$25*365*24 -> 97841585 | I10: =IF($C$6<30,'Maintainance data'!C8,IF($C$6<100,'Maintainance data'!D8,IF($C$6<=250,'Maintainance data'!E8," ")))*H10 -> 2680859.4 | J10: =IF($C$16="Offshore",(($C$8*0.1*$C$23)+(($C$9/100)*H10)),($C$8*$C$23)+(($C$9/100)*H10)) -> 10051143 | K10: =H10-(I10+J10) -> 85109582 | L10: =M10*(IF(G10<0,(1/(1+$C$13/100)^(F10)),(1/(1+$C$13/100)^($C$27))*(1/(1+$C$14/100)^(F10-$C$27)))) -> -15585387 | M10: =IF(M9<0,M9*(1+$C$13/100),M9*(1+$C$14/100))+K10 -> -22374838
B11: Initial Electricity Price (E0) | C11: 0.18 | F11: 6 | G11: =M10 -> -22374838 | H11: =$C$11*(1+$C$12/100)^(F11-1)*$C$25*365*24 -> 1.0126604e+08 | I11: =IF($C$6<30,'Maintainance data'!C9,IF($C$6<100,'Maintainance data'!D9,IF($C$6<=250,'Maintainance data'!E9," ")))*H11 -> 2987348.2 | J11: =IF($C$16="Offshore",(($C$8*0.1*$C$23)+(($C$9/100)*H11)),($C$8*$C$23)+(($C$9/100)*H11)) -> 10393589 | K11: =H11-(I11+J11) -> 87885103 | L11: =M11*(IF(G11<0,(1/(1+$C$13/100)^(F11)),(1/(1+$C$13/100)^($C$27))*(1/(1+$C$14/100)^(F11-$C$27)))) -> 41360778 | M11: =IF(M10<0,M10*(1+$C$13/100),M10*(1+$C$14/100))+K11 -> 63832152
B12: Electricity Inflation rate (j%) | C12: 3.5 | F12: 7 | G12: =M11 -> 63832152 | H12: =$C$11*(1+$C$12/100)^(F12-1)*$C$25*365*24 -> 1.0481035e+08 | I12: =IF($C$6<30,'Maintainance data'!C10,IF($C$6<100,'Maintainance data'!D10,IF($C$6<=250,'Maintainance data'!E10," ")))*H12 -> 3270083 | J12: =IF($C$16="Offshore",(($C$8*0.1*$C$23)+(($C$9/100)*H12)),($C$8*$C$23)+(($C$9/100)*H12)) -> 10748020 | K12: =H12-(I12+J12) -> 90792249 | L12: =M12*(IF(G12<0,(1/(1+$C$13/100)^(F12)),(1/(1+$C$13/100)^($C$27))*(1/(1+$C$14/100)^(F12-$C$27)))) -> 99037135 | M12: =IF(M11<0,M11*(1+$C$13/100),M11*(1+$C$14/100))+K12 -> 1.5590104e+08
B13: Annual Borrowing rate (i1%) | C13: 7.5 | F13: 8 | G13: =M12 -> 1.5590104e+08 | H13: =$C$11*(1+$C$12/100)^(F13-1)*$C$25*365*24 -> 1.0847871e+08 | I13: =IF($C$6<30,'Maintainance data'!C11,IF($C$6<100,'Maintainance data'!D11,IF($C$6<=250,'Maintainance data'!E11," ")))*H13 -> 3536406.1 | J13: =IF($C$16="Offshore",(($C$8*0.1*$C$23)+(($C$9/100)*H13)),($C$8*$C$23)+(($C$9/100)*H13)) -> 11114856 | K13: =H13-(I13+J13) -> 93827452 | L13: =M13*(IF(G13<0,(1/(1+$C$13/100)^(F13)),(1/(1+$C$13/100)^($C$27))*(1/(1+$C$14/100)^(F13-$C$27)))) -> 1.5747291e+08 | M13: =IF(M12<0,M12*(1+$C$13/100),M12*(1+$C$14/100))+K13 -> 2.5284652e+08
B14: Annual Lending rate (i2%) | C14: 2 | F14: 9 | G14: =M13 -> 2.5284652e+08 | H14: =$C$11*(1+$C$12/100)^(F14-1)*$C$25*365*24 -> 1.1227547e+08 | I14: =IF($C$6<30,'Maintainance data'!C12,IF($C$6<100,'Maintainance data'!D12,IF($C$6<=250,'Maintainance data'!E12," ")))*H14 -> 3794910.8 | J14: =IF($C$16="Offshore",(($C$8*0.1*$C$23)+(($C$9/100)*H14)),($C$8*$C$23)+(($C$9/100)*H14)) -> 11494532 | K14: =H14-(I14+J14) -> 96986026 | L14: =M14*(IF(G14<0,(1/(1+$C$13/100)^(F14)),(1/(1+$C$13/100)^($C$27))*(1/(1+$C$14/100)^(F14-$C$27)))) -> 2.1669147e+08 | M14: =IF(M13<0,M13*(1+$C$13/100),M13*(1+$C$14/100))+K14 -> 3.5488947e+08
B15: Subsidy Incentive (S%) | C15: 20 | F15: =IF(F14=" "," ",IF(F14-2=$C$5," ",F14+1)) -> 10 | G15: =IF(F15=" "," ",M14) -> 3.5488947e+08 | H15: =IF(F15=$C$5+2,0,IF(F15=" "," ",$C$11*(1+$C$12/100)^(F15-1)*$C$25*365*24)) -> 1.1620511e+08 | I15: =IF(F15=" "," ",IF($C$6<30,'Maintainance data'!C13,IF($C$6<100,'Maintainance data'!D13,IF($C$6<=250,'Maintainance data'!E13," ")))*H15) -> 4055558.4 | J15: =IF(F15=" "," ",IF($C$16="Offshore",(($C$8*0.1*$C$23)+(($C$9/100)*H15)),($C$8*$C$23)+(($C$9/100)*H15))) -> 11887496 | K15: =IF(F15=" "," ",H15-(I15+J15+IF(N15=" ",0,N15))) -> 1.0026206e+08 | L15: =IF(F15=" "," ",M15*(IF(G15<0,(1/(1+$C$13/100)^(F15)),(1/(1+$C$13/100)^($C$27))*(1/(1+$C$14/100)^(F15-$C$27))))) -> 2.7670997e+08 | M15: =IF(F15=" "," ",IF(M14<0,M14*(1+$C$13/100),M14*(1+$C$14/100))+K15) -> 4.6224932e+08 | N15: =IF(F15=$C$5+2,(IF($C$16="Offshore",$C$10*EXP(0.02*$C$6)*1.3,$C$10*EXP(0.02*$C$6)))*1000000*0.4," ")
B16: Location | C16: Onshore | F16: =IF(F15=" "," ",IF(F15-2=$C$5," ",F15+1)) -> 11 | G16: =IF(F16=" "," ",M15) -> 4.6224932e+08 | H16: =IF(F16=$C$5+2,0,IF(F16=" "," ",$C$11*(1+$C$12/100)^(F16-1)*$C$25*365*24)) -> 1.2027229e+08 | I16: =IF(F16=" "," ",IF($C$6<30,'Maintainance data'!C14,IF($C$6<100,'Maintainance data'!D14,IF($C$6<=250,'Maintainance data'!E14," ")))*H16) -> 4329802.4 | J16: =IF(F16=" "," ",IF($C$16="Offshore",(($C$8*0.1*$C$23)+(($C$9/100)*H16)),($C$8*$C$23)+(($C$9/100)*H16))) -> 12294214 | K16: =IF(F16=" "," ",H16-(I16+J16+IF(N16=" ",0,N16))) -> 1.0364827e+08 | L16: =IF(F16=" "," ",M16*(IF(G16<0,(1/(1+$C$13/100)^(F16)),(1/(1+$C$13/100)^($C$27))*(1/(1+$C$14/100)^(F16-$C$27))))) -> 3.3753894e+08 | M16: =IF(F16=" "," ",IF(M15<0,M15*(1+$C$13/100),M15*(1+$C$14/100))+K16) -> 5.7514258e+08 | N16: =IF(F16=$C$5+2,(IF($C$16="Offshore",$C$10*EXP(0.02*$C$6)*1.3,$C$10*EXP(0.02*$C$6)))*1000000*0.4," ")
F17: =IF(F16=" "," ",IF(F16-2=$C$5," ",F16+1)) -> 12 | G17: =IF(F17=" "," ",M16) -> 5.7514258e+08 | H17: =IF(F17=$C$5+2,0,IF(F17=" "," ",$C$11*(1+$C$12/100)^(F17-1)*$C$25*365*24)) -> 1.2448182e+08 | I17: =IF(F17=" "," ",IF($C$6<30,'Maintainance data'!C15,IF($C$6<100,'Maintainance data'!D15,IF($C$6<=250,'Maintainance data'!E15," ")))*H17) -> 4605827.3 | J17: =IF(F17=" "," ",IF($C$16="Offshore",(($C$8*0.1*$C$23)+(($C$9/100)*H17)),($C$8*$C$23)+(($C$9/100)*H17))) -> 12715167 | K17: =IF(F17=" "," ",H17-(I17+J17+IF(N17=" ",0,N17))) -> 1.0716083e+08 | L17: =IF(F17=" "," ",M17*(IF(G17<0,(1/(1+$C$13/100)^(F17)),(1/(1+$C$13/100)^($C$27))*(1/(1+$C$14/100)^(F17-$C$27))))) -> 3.991962e+08 | M17: =IF(F17=" "," ",IF(M16<0,M16*(1+$C$13/100),M16*(1+$C$14/100))+K17) -> 6.9380626e+08 | N17: =IF(F17=$C$5+2,(IF($C$16="Offshore",$C$10*EXP(0.02*$C$6)*1.3,$C$10*EXP(0.02*$C$6)))*1000000*0.4," ")
F18: =IF(F17=" "," ",IF(F17-2=$C$5," ",F17+1)) -> 13 | G18: =IF(F18=" "," ",M17) -> 6.9380626e+08 | H18: =IF(F18=$C$5+2,0,IF(F18=" "," ",$C$11*(1+$C$12/100)^(F18-1)*$C$25*365*24)) -> 1.2883868e+08 | I18: =IF(F18=" "," ",IF($C$6<30,'Maintainance data'!C16,IF($C$6<100,'Maintainance data'!D16,IF($C$6<=250,'Maintainance data'!E16," ")))*H18) -> 4908753.8 | J18: =IF(F18=" "," ",IF($C$16="Offshore",(($C$8*0.1*$C$23)+(($C$9/100)*H18)),($C$8*$C$23)+(($C$9/100)*H18))) -> 13150853 | K18: =IF(F18=" "," ",H18-(I18+J18+IF(N18=" ",0,N18))) -> 1.1077908e+08 | L18: =IF(F18=" "," ",M18*(IF(G18<0,(1/(1+$C$13/100)^(F18)),(1/(1+$C$13/100)^($C$27))*(1/(1+$C$14/100)^(F18-$C$27))))) -> 4.6168551e+08 | M18: =IF(F18=" "," ",IF(M17<0,M17*(1+$C$13/100),M17*(1+$C$14/100))+K18) -> 8.1846146e+08 | N18: =IF(F18=$C$5+2,(IF($C$16="Offshore",$C$10*EXP(0.02*$C$6)*1.3,$C$10*EXP(0.02*$C$6)))*1000000*0.4," ")
B19: DERIVED CONSTANTS | F19: =IF(F18=" "," ",IF(F18-2=$C$5," ",F18+1)) -> 14 | G19: =IF(F19=" "," ",M18) -> 8.1846146e+08 | H19: =IF(F19=$C$5+2,0,IF(F19=" "," ",$C$11*(1+$C$12/100)^(F19-1)*$C$25*365*24)) -> 1.3334804e+08 | I19: =IF(F19=" "," ",IF($C$6<30,'Maintainance data'!C17,IF($C$6<100,'Maintainance data'!D17,IF($C$6<=250,'Maintainance data'!E17," ")))*H19) -> 5240577.9 | J19: =IF(F19=" "," ",IF($C$16="Offshore",(($C$8*0.1*$C$23)+(($C$9/100)*H19)),($C$8*$C$23)+(($C$9/100)*H19))) -> 13601788 | K19: =IF(F19=" "," ",H19-(I19+J19+IF(N19=" ",0,N19))) -> 1.1450567e+08 | L19: =IF(F19=" "," ",M19*(IF(G19<0,(1/(1+$C$13/100)^(F19)),(1/(1+$C$13/100)^($C$27))*(1/(1+$C$14/100)^(F19-$C$27))))) -> 5.2501046e+08 | M19: =IF(F19=" "," ",IF(M18<0,M18*(1+$C$13/100),M18*(1+$C$14/100))+K19) -> 9.4933636e+08 | N19: =IF(F19=$C$5+2,(IF($C$16="Offshore",$C$10*EXP(0.02*$C$6)*1.3,$C$10*EXP(0.02*$C$6)))*1000000*0.4," ")
F20: =IF(F19=" "," ",IF(F19-2=$C$5," ",F19+1)) -> 15 | G20: =IF(F20=" "," ",M19) -> 9.4933636e+08 | H20: =IF(F20=$C$5+2,0,IF(F20=" "," ",$C$11*(1+$C$12/100)^(F20-1)*$C$25*365*24)) -> 1.3801522e+08 | I20: =IF(F20=" "," ",IF($C$6<30,'Maintainance data'!C18,IF($C$6<100,'Maintainance data'!D18,IF($C$6<=250,'Maintainance data'!E18," ")))*H20) -> 5589616.3 | J20: =IF(F20=" "," ",IF($C$16="Offshore",(($C$8*0.1*$C$23)+(($C$9/100)*H20)),($C$8*$C$23)+(($C$9/100)*H20))) -> 14068507 | K20: =IF(F20=" "," ",H20-(I20+J20+IF(N20=" ",0,N20))) -> 1.183571e+08 | L20: =IF(F20=" "," ",M20*(IF(G20<0,(1/(1+$C$13/100)^(F20)),(1/(1+$C$13/100)^($C$27))*(1/(1+$C$14/100)^(F20-$C$27))))) -> 5.8918192e+08 | M20: =IF(F20=" "," ",IF(M19<0,M19*(1+$C$13/100),M19*(1+$C$14/100))+K20) -> 1.0866802e+09 | N20: =IF(F20=$C$5+2,(IF($C$16="Offshore",$C$10*EXP(0.02*$C$6)*1.3,$C$10*EXP(0.02*$C$6)))*1000000*0.4," ")
B21: Parameters | C21: Value | F21: =IF(F20=" "," ",IF(F20-2=$C$5," ",F20+1)) -> 16 | G21: =IF(F21=" "," ",M20) -> 1.0866802e+09 | H21: =IF(F21=$C$5+2,0,IF(F21=" "," ",$C$11*(1+$C$12/100)^(F21-1)*$C$25*365*24)) -> 1.4284575e+08 | I21: =IF(F21=" "," ",IF($C$6<30,'Maintainance data'!C19,IF($C$6<100,'Maintainance data'!D19,IF($C$6<=250,'Maintainance data'!E19," ")))*H21) -> 5999521.5 | J21: =IF(F21=" "," ",IF($C$16="Offshore",(($C$8*0.1*$C$23)+(($C$9/100)*H21)),($C$8*$C$23)+(($C$9/100)*H21))) -> 14551560 | K21: =IF(F21=" "," ",H21-(I21+J21+IF(N21=" ",0,N21))) -> 1.2229467e+08 | L21: =IF(F21=" "," ",M21*(IF(G21<0,(1/(1+$C$13/100)^(F21)),(1/(1+$C$13/100)^($C$27))*(1/(1+$C$14/100)^(F21-$C$27))))) -> 6.5418816e+08 | M21: =IF(F21=" "," ",IF(M20<0,M20*(1+$C$13/100),M20*(1+$C$14/100))+K21) -> 1.2307085e+09 | N21: =IF(F21=$C$5+2,(IF($C$16="Offshore",$C$10*EXP(0.02*$C$6)*1.3,$C$10*EXP(0.02*$C$6)))*1000000*0.4," ")
B22: FROM INPUT | F22: =IF(F21=" "," ",IF(F21-2=$C$5," ",F21+1)) -> 17 | G22: =IF(F22=" "," ",M21) -> 1.2307085e+09 | H22: =IF(F22=$C$5+2,0,IF(F22=" "," ",$C$11*(1+$C$12/100)^(F22-1)*$C$25*365*24)) -> 1.4784535e+08 | I22: =IF(F22=" "," ",IF($C$6<30,'Maintainance data'!C20,IF($C$6<100,'Maintainance data'!D20,IF($C$6<=250,'Maintainance data'!E20," ")))*H22) -> 6460841.9 | J22: =IF(F22=" "," ",IF($C$16="Offshore",(($C$8*0.1*$C$23)+(($C$9/100)*H22)),($C$8*$C$23)+(($C$9/100)*H22))) -> 15051520 | K22: =IF(F22=" "," ",H22-(I22+J22+IF(N22=" ",0,N22))) -> 1.2633299e+08 | L22: =IF(F22=" "," ",M22*(IF(G22<0,(1/(1+$C$13/100)^(F22)),(1/(1+$C$13/100)^($C$27))*(1/(1+$C$14/100)^(F22-$C$27))))) -> 7.2002426e+08 | M22: =IF(F22=" "," ",IF(M21<0,M21*(1+$C$13/100),M21*(1+$C$14/100))+K22) -> 1.3816556e+09 | N22: =IF(F22=$C$5+2,(IF($C$16="Offshore",$C$10*EXP(0.02*$C$6)*1.3,$C$10*EXP(0.02*$C$6)))*1000000*0.4," ")
B23: Area | C23: =(1.5*C6^2)/4046.86 -> 22.248731 | F23: =IF(F22=" "," ",IF(F22-2=$C$5," ",F22+1)) -> 18 | G23: =IF(F23=" "," ",M22) -> 1.3816556e+09 | H23: =IF(F23=$C$5+2,0,IF(F23=" "," ",$C$11*(1+$C$12/100)^(F23-1)*$C$25*365*24)) -> 1.5301994e+08 | I23: =IF(F23=" "," ",IF($C$6<30,'Maintainance data'!C21,IF($C$6<100,'Maintainance data'!D21,IF($C$6<=250,'Maintainance data'!E21," ")))*H23) -> 7008313.2 | J23: =IF(F23=" "," ",IF($C$16="Offshore",(($C$8*0.1*$C$23)+(($C$9/100)*H23)),($C$8*$C$23)+(($C$9/100)*H23))) -> 15568979 | K23: =IF(F23=" "," ",H23-(I23+J23+IF(N23=" ",0,N23))) -> 1.3044265e+08 | L23: =IF(F23=" "," ",M23*(IF(G23<0,(1/(1+$C$13/100)^(F23)),(1/(1+$C$13/100)^($C$27))*(1/(1+$C$14/100)^(F23-$C$27))))) -> 7.8666914e+08 | M23: =IF(F23=" "," ",IF(M22<0,M22*(1+$C$13/100),M22*(1+$C$14/100))+K23) -> 1.5397314e+09 | N23: =IF(F23=$C$5+2,(IF($C$16="Offshore",$C$10*EXP(0.02*$C$6)*1.3,$C$10*EXP(0.02*$C$6)))*1000000*0.4," ")
B24: Average annual output yield (y) | C24: =-(0.323)+0.147*C7-0.01*(C7)^2+0.0002*(C7)^3 -> 1.147 | F24: =IF(F23=" "," ",IF(F23-2=$C$5," ",F23+1)) -> 19 | G24: =IF(F24=" "," ",M23) -> 1.5397314e+09 | H24: =IF(F24=$C$5+2,0,IF(F24=" "," ",$C$11*(1+$C$12/100)^(F24-1)*$C$25*365*24)) -> 1.5837564e+08 | I24: =IF(F24=" "," ",IF($C$6<30,'Maintainance data'!C22,IF($C$6<100,'Maintainance data'!D22,IF($C$6<=250,'Maintainance data'!E22," ")))*H24) -> 7633705.7 | J24: =IF(F24=" "," ",IF($C$16="Offshore",(($C$8*0.1*$C$23)+(($C$9/100)*H24)),($C$8*$C$23)+(($C$9/100)*H24))) -> 16104549 | K24: =IF(F24=" "," ",H24-(I24+J24+IF(N24=" ",0,N24))) -> 1.3463738e+08 | L24: =IF(F24=" "," ",M24*(IF(G24<0,(1/(1+$C$13/100)^(F24)),(1/(1+$C$13/100)^($C$27))*(1/(1+$C$14/100)^(F24-$C$27))))) -> 8.5410837e+08 | M24: =IF(F24=" "," ",IF(M23<0,M23*(1+$C$13/100),M23*(1+$C$14/100))+K24) -> 1.7051634e+09 | N24: =IF(F24=$C$5+2,(IF($C$16="Offshore",$C$10*EXP(0.02*$C$6)*1.3,$C$10*EXP(0.02*$C$6)))*1000000*0.4," ")
B25: Nominal energy output (N, kWh) | C25: =((C6/2)^2*PI()*C24) -> 54073.623 | F25: =IF(F24=" "," ",IF(F24-2=$C$5," ",F24+1)) -> 20 | G25: =IF(F25=" "," ",M24) -> 1.7051634e+09 | H25: =IF(F25=$C$5+2,0,IF(F25=" "," ",$C$11*(1+$C$12/100)^(F25-1)*$C$25*365*24)) -> 1.6391878e+08 | I25: =IF(F25=" "," ",IF($C$6<30,'Maintainance data'!C23,IF($C$6<100,'Maintainance data'!D23,IF($C$6<=250,'Maintainance data'!E23," ")))*H25) -> 8392641.8 | J25: =IF(F25=" "," ",IF($C$16="Offshore",(($C$8*0.1*$C$23)+(($C$9/100)*H25)),($C$8*$C$23)+(($C$9/100)*H25))) -> 16658863 | K25: =IF(F25=" "," ",H25-(I25+J25+IF(N25=" ",0,N25))) -> 1.3886728e+08 | L25: =IF(F25=" "," ",M25*(IF(G25<0,(1/(1+$C$13/100)^(F25)),(1/(1+$C$13/100)^($C$27))*(1/(1+$C$14/100)^(F25-$C$27))))) -> 9.2230246e+08 | M25: =IF(F25=" "," ",IF(M24<0,M24*(1+$C$13/100),M24*(1+$C$14/100))+K25) -> 1.8781339e+09 | N25: =IF(F25=$C$5+2,(IF($C$16="Offshore",$C$10*EXP(0.02*$C$6)*1.3,$C$10*EXP(0.02*$C$6)))*1000000*0.4," ")
B26: FROM BALANCE SHEET | F26: =IF(F25=" "," ",IF(F25-2=$C$5," ",F25+1)) -> 21 | G26: =IF(F26=" "," ",M25) -> 1.8781339e+09 | H26: =IF(F26=$C$5+2,0,IF(F26=" "," ",$C$11*(1+$C$12/100)^(F26-1)*$C$25*365*24)) -> 1.6965594e+08 | I26: =IF(F26=" "," ",IF($C$6<30,'Maintainance data'!C24,IF($C$6<100,'Maintainance data'!D24,IF($C$6<=250,'Maintainance data'!E24," ")))*H26) -> 9314111.2 | J26: =IF(F26=" "," ",IF($C$16="Offshore",(($C$8*0.1*$C$23)+(($C$9/100)*H26)),($C$8*$C$23)+(($C$9/100)*H26))) -> 17232579 | K26: =IF(F26=" "," ",H26-(I26+J26+IF(N26=" ",0,N26))) -> 1.4310925e+08 | L26: =IF(F26=" "," ",M26*(IF(G26<0,(1/(1+$C$13/100)^(F26)),(1/(1+$C$13/100)^($C$27))*(1/(1+$C$14/100)^(F26-$C$27))))) -> 9.9120169e+08 | M26: =IF(F26=" "," ",IF(M25<0,M25*(1+$C$13/100),M25*(1+$C$14/100))+K26) -> 2.0588059e+09 | N26: =IF(F26=$C$5+2,(IF($C$16="Offshore",$C$10*EXP(0.02*$C$6)*1.3,$C$10*EXP(0.02*$C$6)))*1000000*0.4," ")
B27: DPP | C27: {=INDEX(F5:F45,MATCH(TRUE, (L5:L45 > 0),0))} -> 6 | F27: =IF(F26=" "," ",IF(F26-2=$C$5," ",F26+1)) -> 22 | G27: =IF(F27=" "," ",M26) -> 2.0588059e+09 | H27: =IF(F27=$C$5+2,0,IF(F27=" "," ",$C$11*(1+$C$12/100)^(F27-1)*$C$25*365*24)) -> 1.755939e+08 | I27: =IF(F27=" "," ",IF($C$6<30,'Maintainance data'!C25,IF($C$6<100,'Maintainance data'!D25,IF($C$6<=250,'Maintainance data'!E25," ")))*H27) -> 10412718 | J27: =IF(F27=" "," ",IF($C$16="Offshore",(($C$8*0.1*$C$23)+(($C$9/100)*H27)),($C$8*$C$23)+(($C$9/100)*H27))) -> 17826375 | K27: =IF(F27=" "," ",H27-(I27+J27+IF(N27=" ",0,N27))) -> 1.4735481e+08 | L27: =IF(F27=" "," ",M27*(IF(G27<0,(1/(1+$C$13/100)^(F27)),(1/(1+$C$13/100)^($C$27))*(1/(1+$C$14/100)^(F27-$C$27))))) -> 1.0607539e+09 | M27: =IF(F27=" "," ",IF(M26<0,M26*(1+$C$13/100),M26*(1+$C$14/100))+K27) -> 2.2473368e+09 | N27: =IF(F27=$C$5+2,(IF($C$16="Offshore",$C$10*EXP(0.02*$C$6)*1.3,$C$10*EXP(0.02*$C$6)))*1000000*0.4," ")
B28: AROI | C28: =CONCATENATE(ROUND(-((VLOOKUP(C5+2,F5:N47,7,0)-G5)/G5)*(1/(C5+2))*100,4)," %") -> 22.3866 % | F28: =IF(F27=" "," ",IF(F27-2=$C$5," ",F27+1)) -> 23 | G28: =IF(F28=" "," ",M27) -> 2.2473368e+09 | H28: =IF(F28=$C$5+2,0,IF(F28=" "," ",$C$11*(1+$C$12/100)^(F28-1)*$C$25*365*24)) -> 1.8173969e+08 | I28: =IF(F28=" "," ",IF($C$6<30,'Maintainance data'!C26,IF($C$6<100,'Maintainance data'!D26,IF($C$6<=250,'Maintainance data'!E26," ")))*H28) -> 11776732 | J28: =IF(F28=" "," ",IF($C$16="Offshore",(($C$8*0.1*$C$23)+(($C$9/100)*H28)),($C$8*$C$23)+(($C$9/100)*H28))) -> 18440953 | K28: =IF(F28=" "," ",H28-(I28+J28+IF(N28=" ",0,N28))) -> 1.51522e+08 | L28: =IF(F28=" "," ",M28*(IF(G28<0,(1/(1+$C$13/100)^(F28)),(1/(1+$C$13/100)^($C$27))*(1/(1+$C$14/100)^(F28-$C$27))))) -> 1.1308707e+09 | M28: =IF(F28=" "," ",IF(M27<0,M27*(1+$C$13/100),M27*(1+$C$14/100))+K28) -> 2.4438055e+09 | N28: =IF(F28=$C$5+2,(IF($C$16="Offshore",$C$10*EXP(0.02*$C$6)*1.3,$C$10*EXP(0.02*$C$6)))*1000000*0.4," ")
F29: =IF(F28=" "," ",IF(F28-2=$C$5," ",F28+1)) -> 24 | G29: =IF(F29=" "," ",M28) -> 2.4438055e+09 | H29: =IF(F29=$C$5+2,0,IF(F29=" "," ",$C$11*(1+$C$12/100)^(F29-1)*$C$25*365*24)) -> 1.8810058e+08 | I29: =IF(F29=" "," ",IF($C$6<30,'Maintainance data'!C27,IF($C$6<100,'Maintainance data'!D27,IF($C$6<=250,'Maintainance data'!E27," ")))*H29) -> 13468001 | J29: =IF(F29=" "," ",IF($C$16="Offshore",(($C$8*0.1*$C$23)+(($C$9/100)*H29)),($C$8*$C$23)+(($C$9/100)*H29))) -> 19077042 | K29: =IF(F29=" "," ",H29-(I29+J29+IF(N29=" ",0,N29))) -> 1.5555553e+08 | L29: =IF(F29=" "," ",M29*(IF(G29<0,(1/(1+$C$13/100)^(F29)),(1/(1+$C$13/100)^($C$27))*(1/(1+$C$14/100)^(F29-$C$27))))) -> 1.2014425e+09 | M29: =IF(F29=" "," ",IF(M28<0,M28*(1+$C$13/100),M28*(1+$C$14/100))+K29) -> 2.6482372e+09 | N29: =IF(F29=$C$5+2,(IF($C$16="Offshore",$C$10*EXP(0.02*$C$6)*1.3,$C$10*EXP(0.02*$C$6)))*1000000*0.4," ")
F30: =IF(F29=" "," ",IF(F29-2=$C$5," ",F29+1)) -> 25 | G30: =IF(F30=" "," ",M29) -> 2.6482372e+09 | H30: =IF(F30=$C$5+2,0,IF(F30=" "," ",$C$11*(1+$C$12/100)^(F30-1)*$C$25*365*24)) -> 1.946841e+08 | I30: =IF(F30=" "," ",IF($C$6<30,'Maintainance data'!C28,IF($C$6<100,'Maintainance data'!D28,IF($C$6<=250,'Maintainance data'!E28," ")))*H30) -> 15535791 | J30: =IF(F30=" "," ",IF($C$16="Offshore",(($C$8*0.1*$C$23)+(($C$9/100)*H30)),($C$8*$C$23)+(($C$9/100)*H30))) -> 19735394 | K30: =IF(F30=" "," ",H30-(I30+J30+IF(N30=" ",0,N30))) -> 1.5941291e+08 | L30: =IF(F30=" "," ",M30*(IF(G30<0,(1/(1+$C$13/100)^(F30)),(1/(1+$C$13/100)^($C$27))*(1/(1+$C$14/100)^(F30-$C$27))))) -> 1.2723463e+09 | M30: =IF(F30=" "," ",IF(M29<0,M29*(1+$C$13/100),M29*(1+$C$14/100))+K30) -> 2.8606148e+09 | N30: =IF(F30=$C$5+2,(IF($C$16="Offshore",$C$10*EXP(0.02*$C$6)*1.3,$C$10*EXP(0.02*$C$6)))*1000000*0.4," ")
F31: =IF(F30=" "," ",IF(F30-2=$C$5," ",F30+1)) -> 26 | G31: =IF(F31=" "," ",M30) -> 2.8606148e+09 | H31: =IF(F31=$C$5+2,0,IF(F31=" "," ",$C$11*(1+$C$12/100)^(F31-1)*$C$25*365*24)) -> 2.0149804e+08 | I31: =IF(F31=" "," ",IF($C$6<30,'Maintainance data'!C29,IF($C$6<100,'Maintainance data'!D29,IF($C$6<=250,'Maintainance data'!E29," ")))*H31) -> 18114674 | J31: =IF(F31=" "," ",IF($C$16="Offshore",(($C$8*0.1*$C$23)+(($C$9/100)*H31)),($C$8*$C$23)+(($C$9/100)*H31))) -> 20416789 | K31: =IF(F31=" "," ",H31-(I31+J31+IF(N31=" ",0,N31))) -> 1.6296658e+08 | L31: =IF(F31=" "," ",M31*(IF(G31<0,(1/(1+$C$13/100)^(F31)),(1/(1+$C$13/100)^($C$27))*(1/(1+$C$14/100)^(F31-$C$27))))) -> 1.3434094e+09 | M31: =IF(F31=" "," ",IF(M30<0,M30*(1+$C$13/100),M30*(1+$C$14/100))+K31) -> 3.0807937e+09 | N31: =IF(F31=$C$5+2,(IF($C$16="Offshore",$C$10*EXP(0.02*$C$6)*1.3,$C$10*EXP(0.02*$C$6)))*1000000*0.4," ")
F32: =IF(F31=" "," ",IF(F31-2=$C$5," ",F31+1)) -> 27 | G32: =IF(F32=" "," ",M31) -> 3.0807937e+09 | H32: =IF(F32=$C$5+2,0,IF(F32=" "," ",$C$11*(1+$C$12/100)^(F32-1)*$C$25*365*24)) -> 2.0855047e+08 | I32: =IF(F32=" "," ",IF($C$6<30,'Maintainance data'!C30,IF($C$6<100,'Maintainance data'!D30,IF($C$6<=250,'Maintainance data'!E30," ")))*H32) -> 21293003 | J32: =IF(F32=" "," ",IF($C$16="Offshore",(($C$8*0.1*$C$23)+(($C$9/100)*H32)),($C$8*$C$23)+(($C$9/100)*H32))) -> 21122032 | K32: =IF(F32=" "," ",H32-(I32+J32+IF(N32=" ",0,N32))) -> 1.6613544e+08 | L32: =IF(F32=" "," ",M32*(IF(G32<0,(1/(1+$C$13/100)^(F32)),(1/(1+$C$13/100)^($C$27))*(1/(1+$C$14/100)^(F32-$C$27))))) -> 1.4144339e+09 | M32: =IF(F32=" "," ",IF(M31<0,M31*(1+$C$13/100),M31*(1+$C$14/100))+K32) -> 3.308545e+09 | N32: =IF(F32=$C$5+2,(IF($C$16="Offshore",$C$10*EXP(0.02*$C$6)*1.3,$C$10*EXP(0.02*$C$6)))*1000000*0.4," ")
F33: =IF(F32=" "," ",IF(F32-2=$C$5," ",F32+1)) -> 28 | G33: =IF(F33=" "," ",M32) -> 3.308545e+09 | H33: =IF(F33=$C$5+2,0,IF(F33=" "," ",$C$11*(1+$C$12/100)^(F33-1)*$C$25*365*24)) -> 2.1584974e+08 | I33: =IF(F33=" "," ",IF($C$6<30,'Maintainance data'!C31,IF($C$6<100,'Maintainance data'!D31,IF($C$6<=250,'Maintainance data'!E31," ")))*H33) -> 25232834 | J33: =IF(F33=" "," ",IF($C$16="Offshore",(($C$8*0.1*$C$23)+(($C$9/100)*H33)),($C$8*$C$23)+(($C$9/100)*H33))) -> 21851958 | K33: =IF(F33=" "," ",H33-(I33+J33+IF(N33=" ",0,N33))) -> 1.6876494e+08 | L33: =IF(F33=" "," ",M33*(IF(G33<0,(1/(1+$C$13/100)^(F33)),(1/(1+$C$13/100)^($C$27))*(1/(1+$C$14/100)^(F33-$C$27))))) -> 1.4851678e+09 | M33: =IF(F33=" "," ",IF(M32<0,M32*(1+$C$13/100),M32*(1+$C$14/100))+K33) -> 3.5434808e+09 | N33: =IF(F33=$C$5+2,(IF($C$16="Offshore",$C$10*EXP(0.02*$C$6)*1.3,$C$10*EXP(0.02*$C$6)))*1000000*0.4," ")
F34: =IF(F33=" "," ",IF(F33-2=$C$5," ",F33+1)) -> 29 | G34: =IF(F34=" "," ",M33) -> 3.5434808e+09 | H34: =IF(F34=$C$5+2,0,IF(F34=" "," ",$C$11*(1+$C$12/100)^(F34-1)*$C$25*365*24)) -> 2.2340448e+08 | I34: =IF(F34=" "," ",IF($C$6<30,'Maintainance data'!C32,IF($C$6<100,'Maintainance data'!D32,IF($C$6<=250,'Maintainance data'!E32," ")))*H34) -> 30025562 | J34: =IF(F34=" "," ",IF($C$16="Offshore",(($C$8*0.1*$C$23)+(($C$9/100)*H34)),($C$8*$C$23)+(($C$9/100)*H34))) -> 22607433 | K34: =IF(F34=" "," ",H34-(I34+J34+IF(N34=" ",0,N34))) -> 1.7077148e+08 | L34: =IF(F34=" "," ",M34*(IF(G34<0,(1/(1+$C$13/100)^(F34)),(1/(1+$C$13/100)^($C$27))*(1/(1+$C$14/100)^(F34-$C$27))))) -> 1.5553393e+09 | M34: =IF(F34=" "," ",IF(M33<0,M33*(1+$C$13/100),M33*(1+$C$14/100))+K34) -> 3.7851219e+09 | N34: =IF(F34=$C$5+2,(IF($C$16="Offshore",$C$10*EXP(0.02*$C$6)*1.3,$C$10*EXP(0.02*$C$6)))*1000000*0.4," ")
F35: =IF(F34=" "," ",IF(F34-2=$C$5," ",F34+1)) -> 30 | G35: =IF(F35=" "," ",M34) -> 3.7851219e+09 | H35: =IF(F35=$C$5+2,0,IF(F35=" "," ",$C$11*(1+$C$12/100)^(F35-1)*$C$25*365*24)) -> 2.3122363e+08 | I35: =IF(F35=" "," ",IF($C$6<30,'Maintainance data'!C33,IF($C$6<100,'Maintainance data'!D33,IF($C$6<=250,'Maintainance data'!E33," ")))*H35) -> 35862786 | J35: =IF(F35=" "," ",IF($C$16="Offshore",(($C$8*0.1*$C$23)+(($C$9/100)*H35)),($C$8*$C$23)+(($C$9/100)*H35))) -> 23389348 | K35: =IF(F35=" "," ",H35-(I35+J35+IF(N35=" ",0,N35))) -> 1.719715e+08 | L35: =IF(F35=" "," ",M35*(IF(G35<0,(1/(1+$C$13/100)^(F35)),(1/(1+$C$13/100)^($C$27))*(1/(1+$C$14/100)^(F35-$C$27))))) -> 1.6246183e+09 | M35: =IF(F35=" "," ",IF(M34<0,M34*(1+$C$13/100),M34*(1+$C$14/100))+K35) -> 4.0327959e+09 | N35: =IF(F35=$C$5+2,(IF($C$16="Offshore",$C$10*EXP(0.02*$C$6)*1.3,$C$10*EXP(0.02*$C$6)))*1000000*0.4," ")
F36: =IF(F35=" "," ",IF(F35-2=$C$5," ",F35+1)) -> 31 | G36: =IF(F36=" "," ",M35) -> 4.0327959e+09 | H36: =IF(F36=$C$5+2,0,IF(F36=" "," ",$C$11*(1+$C$12/100)^(F36-1)*$C$25*365*24)) -> 2.3931646e+08 | I36: =IF(F36=" "," ",IF($C$6<30,'Maintainance data'!C34,IF($C$6<100,'Maintainance data'!D34,IF($C$6<=250,'Maintainance data'!E34," ")))*H36) -> 42885510 | J36: =IF(F36=" "," ",IF($C$16="Offshore",(($C$8*0.1*$C$23)+(($C$9/100)*H36)),($C$8*$C$23)+(($C$9/100)*H36))) -> 24198631 | K36: =IF(F36=" "," ",H36-(I36+J36+IF(N36=" ",0,N36))) -> 1.7223232e+08 | L36: =IF(F36=" "," ",M36*(IF(G36<0,(1/(1+$C$13/100)^(F36)),(1/(1+$C$13/100)^($C$27))*(1/(1+$C$14/100)^(F36-$C$27))))) -> 1.6926419e+09 | M36: =IF(F36=" "," ",IF(M35<0,M35*(1+$C$13/100),M35*(1+$C$14/100))+K36) -> 4.2856841e+09 | N36: =IF(F36=$C$5+2,(IF($C$16="Offshore",$C$10*EXP(0.02*$C$6)*1.3,$C$10*EXP(0.02*$C$6)))*1000000*0.4," ")
F37: =IF(F36=" "," ",IF(F36-2=$C$5," ",F36+1)) -> 32 | G37: =IF(F37=" "," ",M36) -> 4.2856841e+09 | H37: =IF(F37=$C$5+2,0,IF(F37=" "," ",$C$11*(1+$C$12/100)^(F37-1)*$C$25*365*24)) -> 2.4769254e+08 | I37: =IF(F37=" "," ",IF($C$6<30,'Maintainance data'!C35,IF($C$6<100,'Maintainance data'!D35,IF($C$6<=250,'Maintainance data'!E35," ")))*H37) -> 51148509 | J37: =IF(F37=" "," ",IF($C$16="Offshore",(($C$8*0.1*$C$23)+(($C$9/100)*H37)),($C$8*$C$23)+(($C$9/100)*H37))) -> 25036239 | K37: =IF(F37=" "," ",H37-(I37+J37+IF(N37=" ",0,N37))) -> 1.7150779e+08 | L37: =IF(F37=" "," ",M37*(IF(G37<0,(1/(1+$C$13/100)^(F37)),(1/(1+$C$13/100)^($C$27))*(1/(1+$C$14/100)^(F37-$C$27))))) -> 1.7590511e+09 | M37: =IF(F37=" "," ",IF(M36<0,M36*(1+$C$13/100),M36*(1+$C$14/100))+K37) -> 4.5429056e+09 | N37: =IF(F37=$C$5+2,(IF($C$16="Offshore",$C$10*EXP(0.02*$C$6)*1.3,$C$10*EXP(0.02*$C$6)))*1000000*0.4," ")
F38: =IF(F37=" "," ",IF(F37-2=$C$5," ",F37+1)) -> 33 | G38: =IF(F38=" "," ",M37) -> 4.5429056e+09 | H38: =IF(F38=$C$5+2,0,IF(F38=" "," ",$C$11*(1+$C$12/100)^(F38-1)*$C$25*365*24)) -> 2.5636178e+08 | I38: =IF(F38=" "," ",IF($C$6<30,'Maintainance data'!C36,IF($C$6<100,'Maintainance data'!D36,IF($C$6<=250,'Maintainance data'!E36," ")))*H38) -> 60655196 | J38: =IF(F38=" "," ",IF($C$16="Offshore",(($C$8*0.1*$C$23)+(($C$9/100)*H38)),($C$8*$C$23)+(($C$9/100)*H38))) -> 25903162 | K38: =IF(F38=" "," ",H38-(I38+J38+IF(N38=" ",0,N38))) -> 1.6980342e+08 | L38: =IF(F38=" "," ",M38*(IF(G38<0,(1/(1+$C$13/100)^(F38)),(1/(1+$C$13/100)^($C$27))*(1/(1+$C$14/100)^(F38-$C$27))))) -> 1.8235112e+09 | M38: =IF(F38=" "," ",IF(M37<0,M37*(1+$C$13/100),M37*(1+$C$14/100))+K38) -> 4.8035671e+09 | N38: =IF(F38=$C$5+2,(IF($C$16="Offshore",$C$10*EXP(0.02*$C$6)*1.3,$C$10*EXP(0.02*$C$6)))*1000000*0.4," ")
F39: =IF(F38=" "," ",IF(F38-2=$C$5," ",F38+1)) -> 34 | G39: =IF(F39=" "," ",M38) -> 4.8035671e+09 | H39: =IF(F39=$C$5+2,0,IF(F39=" "," ",$C$11*(1+$C$12/100)^(F39-1)*$C$25*365*24)) -> 2.6533444e+08 | I39: =IF(F39=" "," ",IF($C$6<30,'Maintainance data'!C37,IF($C$6<100,'Maintainance data'!D37,IF($C$6<=250,'Maintainance data'!E37," ")))*H39) -> 71321897 | J39: =IF(F39=" "," ",IF($C$16="Offshore",(($C$8*0.1*$C$23)+(($C$9/100)*H39)),($C$8*$C$23)+(($C$9/100)*H39))) -> 26800429 | K39: =IF(F39=" "," ",H39-(I39+J39+IF(N39=" ",0,N39))) -> 1.6721211e+08 | L39: =IF(F39=" "," ",M39*(IF(G39<0,(1/(1+$C$13/100)^(F39)),(1/(1+$C$13/100)^($C$27))*(1/(1+$C$14/100)^(F39-$C$27))))) -> 1.885743e+09 | M39: =IF(F39=" "," ",IF(M38<0,M38*(1+$C$13/100),M38*(1+$C$14/100))+K39) -> 5.0668506e+09 | N39: =IF(F39=$C$5+2,(IF($C$16="Offshore",$C$10*EXP(0.02*$C$6)*1.3,$C$10*EXP(0.02*$C$6)))*1000000*0.4," ")
F40: =IF(F39=" "," ",IF(F39-2=$C$5," ",F39+1)) -> 35 | G40: =IF(F40=" "," ",M39) -> 5.0668506e+09 | H40: =IF(F40=$C$5+2,0,IF(F40=" "," ",$C$11*(1+$C$12/100)^(F40-1)*$C$25*365*24)) -> 2.7462114e+08 | I40: =IF(F40=" "," ",IF($C$6<30,'Maintainance data'!C38,IF($C$6<100,'Maintainance data'!D38,IF($C$6<=250,'Maintainance data'!E38," ")))*H40) -> 82770813 | J40: =IF(F40=" "," ",IF($C$16="Offshore",(($C$8*0.1*$C$23)+(($C$9/100)*H40)),($C$8*$C$23)+(($C$9/100)*H40))) -> 27729099 | K40: =IF(F40=" "," ",H40-(I40+J40+IF(N40=" ",0,N40))) -> 1.6412123e+08 | L40: =IF(F40=" "," ",M40*(IF(G40<0,(1/(1+$C$13/100)^(F40)),(1/(1+$C$13/100)^($C$27))*(1/(1+$C$14/100)^(F40-$C$27))))) -> 1.9456267e+09 | M40: =IF(F40=" "," ",IF(M39<0,M39*(1+$C$13/100),M39*(1+$C$14/100))+K40) -> 5.3323088e+09 | N40: =IF(F40=$C$5+2,(IF($C$16="Offshore",$C$10*EXP(0.02*$C$6)*1.3,$C$10*EXP(0.02*$C$6)))*1000000*0.4," ")
... F47: =IF(F46=" "," ",IF(F46-2=$C$5," ",F46+1)) | G47: =IF(F47=" "," ",M46) | H47: =IF(F47=$C$5+2,0,IF(F47=" "," ",$C$11*(1+$C$12/100)^(F47-1)*$C$25*365*24)) | I47: =IF(F47=" "," ",IF($C$6<30,'Maintainance data'!C45,IF($C$6<100,'Maintainance data'!D45,IF($C$6<=250,'Maintainance data'!E45," ")))*H47) | J47: =IF(F47=" "," ",IF($C$16="Offshore",(($C$8*0.1*$C$23)+(($C$9/100)*H47)),($C$8*$C$23)+(($C$9/100)*H47))) | K47: =IF(F47=" "," ",H47-(I47+J47+IF(N47=" ",0,N47))) | L47: =IF(F47=" "," ",M47*(IF(G47<0,(1/(1+$C$13/100)^(F47)),(1/(1+$C$13/100)^($C$27))*(1/(1+$C$14/100)^(F47-$C$27))))) | M47: =IF(F47=" "," ",IF(M46<0,M46*(1+$C$13/100),M46*(1+$C$14/100))+K47) | N47: =IF(F47=$C$5+2,(IF($C$16="Offshore",$C$10*EXP(0.02*$C$6)*1.3,$C$10*EXP(0.02*$C$6)))*1000000*0.4," ")

Sheet Maintainance data
B2: Table 1: Maintenance rate data
B3: Expected maintenance rates (per gross revenue)
B4: Year | C4: Small 15 ≤ d < 30 | D4: Medium 30 ≤ d < 100 | E4: Large 100 ≤ d < 250
B5: 1 | C5: 0.0004 | D5: 0.0072 | E5: 0.0107
B6: 2 | C6: 0.0009 | D6: 0.0092 | E6: 0.0198
B7: 3 | C7: 0.0013 | D7: 0.0108 | E7: 0.0244
B8: 4 | C8: 0.0018 | D8: 0.012 | E8: 0.0274
B9: 5 | C9: 0.0024 | D9: 0.013 | E9: 0.0295
B10: 6 | C10: 0.003 | D10: 0.0139 | E10: 0.0312
B11: 7 | C11: 0.0037 | D11: 0.0146 | E11: 0.0326
B12: 8 | C12: 0.0045 | D12: 0.0153 | E12: 0.0338
B13: 9 | C13: 0.0054 | D13: 0.0158 | E13: 0.0349
B14: 10 | C14: 0.0063 | D14: 0.0163 | E14: 0.036
B15: 11 | C15: 0.0073 | D15: 0.0168 | E15: 0.037
B16: 12 | C16: 0.0085 | D16: 0.0172 | E16: 0.0381
... B44: 40 | C44: 0.1737 | D44: 0.3201 | E44: 0.3449
